wykop/__init__.py
wykop/utils.py
wykop/api/__init__.py
wykop/api/clients.py
wykop/api/decorators.py
wykop/api/models.py
wykop/api/exceptions/__init__.py
wykop/api/exceptions/base.py
wykop/api/exceptions/resolvers.py
wykop/api/parsers/__init__.py
wykop/api/parsers/base.py
wykop/api/parsers/json.py
wykop/api/requesters/__init__.py
wykop/api/requesters/base.py
wykop/api/requesters/requests.py
wykop/api/requesters/urllib.py
wykop/api/v1/__init__.py
wykop/api/v1/clients.py
wykop/api/v2/__init__.py
wykop/api/v2/clients.py
wykop_sdk-0.5.0.dist-info/DESCRIPTION.rst
wykop_sdk-0.5.0.dist-info/METADATA
wykop_sdk-0.5.0.dist-info/RECORD
wykop_sdk-0.5.0.dist-info/WHEEL
wykop_sdk-0.5.0.dist-info/metadata.json
wykop_sdk-0.5.0.dist-info/top_level.txt
