Metadata-Version: 2.0
Name: wykop-sdk
Version: 0.5.0
Summary: Client library for Wykop API
Home-page: https://github.com/p1c2u/wykop-sdk
Author: Artur Maciag
Author-email: maciag.artur@gmail.com
License: BSD
Platform: UNKNOWN
Classifier: Programming Language :: Python :: 2.7
Classifier: Programming Language :: Python :: 3.3
Classifier: Programming Language :: Python :: 3.4
Classifier: Programming Language :: Python :: 3.5
Classifier: Programming Language :: Python :: 3.6
Classifier: License :: OSI Approved :: Apache Software License
Classifier: Programming Language :: Python
Classifier: Topic :: Software Development :: Libraries :: Python Modules
Requires-Dist: six (==1.10.0)
